echidna_obj/__init__.py
echidna_obj/parse_simple_.py
echidna_obj/parse_tube_.py
echidna_obj/parse_wire_.py
echidna_obj-1.1.1.dist-info/LICENSE
echidna_obj-1.1.1.dist-info/METADATA
echidna_obj-1.1.1.dist-info/WHEEL
echidna_obj-1.1.1.dist-info/top_level.txt
echidna_obj-1.1.1.dist-info/RECORD
