Metadata-Version: 2.1
Name: echidna-obj
Version: 1.1.1
Summary: A Parser for 3D .obj data models (.obj file format) - working with ADENITA and SAMSON
Home-page: https://gitlab.com/chris_h_/echidna
Author: Christiane Huetter
Author-email: christianevrhuetter@gmail.com
License: MIT
Platform: UNKNOWN
Classifier: Programming Language :: Python :: 3
Requires-Dist: scikit-learn
